pushtunes/__init__.py
pushtunes/cli.py
pushtunes/cli/__init__.py
pushtunes/cli/main.py
pushtunes/clients/__init__.py
pushtunes/clients/jellyfin.py
pushtunes/clients/subsonic.py
pushtunes/models/__init__.py
pushtunes/models/album.py
pushtunes/models/compare_status.py
pushtunes/models/playlist.py
pushtunes/models/push_status.py
pushtunes/models/track.py
pushtunes/services/__init__.py
pushtunes/services/album_comparer.py
pushtunes/services/csv.py
pushtunes/services/deleter.py
pushtunes/services/jellyfin.py
pushtunes/services/job_runner.py
pushtunes/services/mappings_manager.py
pushtunes/services/music_service.py
pushtunes/services/playlist_comparer.py
pushtunes/services/playlist_pusher.py
pushtunes/services/pusher.py
pushtunes/services/spotify.py
pushtunes/services/subsonic.py
pushtunes/services/tidal.py
pushtunes/services/track_comparer.py
pushtunes/services/ytm.py
pushtunes/sources/__init__.py
pushtunes/sources/base.py
pushtunes/sources/csv.py
pushtunes/sources/jellyfin.py
pushtunes/sources/spotify.py
pushtunes/sources/subsonic.py
pushtunes/sources/tidal.py
pushtunes/sources/ytm.py
pushtunes/utils/__init__.py
pushtunes/utils/artist_utils.py
pushtunes/utils/cache_manager.py
pushtunes/utils/csv_manager.py
pushtunes/utils/csv_utils.py
pushtunes/utils/deletion_confirm.py
pushtunes/utils/deletion_manager.py
pushtunes/utils/filters.py
pushtunes/utils/logging.py
pushtunes/utils/profile_manager.py
pushtunes/utils/reporting.py
pushtunes/utils/similarity.py
pushtunes/utils/cli/__init__.py
pushtunes/utils/cli/commands/__init__.py
pushtunes/utils/cli/commands/compare.py
pushtunes/utils/cli/commands/delete.py
pushtunes/utils/cli/commands/push.py
pushtunes/utils/cli/commands/shared.py
pushtunes-2.9.0.dist-info/licenses/LICENSE
pushtunes-2.9.0.dist-info/METADATA
pushtunes-2.9.0.dist-info/WHEEL
pushtunes-2.9.0.dist-info/entry_points.txt
pushtunes-2.9.0.dist-info/top_level.txt
pushtunes-2.9.0.dist-info/RECORD
