Metadata-Version: 2.4
Name: pushtunes
Version: 2.9.0
Summary: Push music (albums, tracks, playlists) from Subsonic, Jellyfin or plain CSV files to Spotify and YouTube Music
Author-email: Psy-Q <rca@psy-q.ch>
License-Expression: AGPL-3.0-or-later
Project-URL: Homepage, https://codeberg.org/psy-q/pushtunes
Project-URL: Repository, https://codeberg.org/psy-q/pushtunes
Project-URL: Issues, https://codeberg.org/psy-q/pushtunes/issues
Classifier: Development Status :: 4 - Beta
Classifier: Intended Audience :: End Users/Desktop
Classifier: Topic :: Multimedia :: Sound/Audio
Classifier: Programming Language :: Python :: 3.10
Classifier: Programming Language :: Python :: 3.11
Classifier: Programming Language :: Python :: 3.12
Classifier: Programming Language :: Python :: 3.13
Classifier: Programming Language :: Python :: 3.14
Requires-Python: >=3.10
License-File: LICENSE
Requires-Dist: spotipy
Requires-Dist: deepdiff
Requires-Dist: thefuzz
Requires-Dist: platformdirs
Requires-Dist: ytmusicapi
Requires-Dist: orjson>=3.10.15
Requires-Dist: typer
Requires-Dist: jellyfin-apiclient-python
Requires-Dist: rich
Requires-Dist: pyyaml
Requires-Dist: tomli>=2.0.0; python_version < "3.11"
Requires-Dist: tidalapi>=0.8.9
Requires-Dist: typing-extensions>=4.15.0
Requires-Dist: py-opensonic>=7.0.3
Provides-Extra: dev
Requires-Dist: pytest; extra == "dev"
Requires-Dist: black; extra == "dev"
Requires-Dist: flake8; extra == "dev"
Requires-Dist: mypy; extra == "dev"
Dynamic: license-file
